[1,["a9wYedHNJA6J8dBc9VMWoU@6c48a"],["_textureSource"],["cc.SpriteFrame"],0,[{"name":"friend_jiu_mist","rect":{"x":2,"y":2,"width":2024,"height":275},"offset":{"x":-10,"y":116.5},"originalSize":{"width":2048,"height":512},"rotated":false,"capInsets":[0,0,0,0],"vertices":{"rawPosition":[-1012,-137.5,0,1012,-137.5,0,-1012,137.5,0,1012,137.5,0],"indexes":[0,1,2,2,1,3],"uv":[2,510,2026,510,2,235,2026,235],"nuv":[0.0009765625,0.458984375,0.9892578125,0.458984375,0.0009765625,0.99609375,0.9892578125,0.99609375],"minPos":{"x":-1012,"y":-137.5,"z":0},"maxPos":{"x":1012,"y":137.5,"z":0}},"packable":true,"pixelsToUnit":100,"pivot":{"x":0.5,"y":0.5},"meshType":0}],[0],0,[0],[0],[0]]
